{
  "project_info": {
    "project_number": "109465422941",
    "project_id": "glublood-reminder",
    "storage_bucket": "glublood-reminder.firebasestorage.app"
  },
  "client": [
    {
      "client_info": {
        "mobilesdk_app_id": "1:109465422941:android:06ccbd43f9fb83e85c91b4",
        "android_client_info": {
          "package_name": "com.glubloodfe"
        }
      },
      "oauth_client": [],
      "api_key": [
        {
          "current_key": "AIzaSyC8y0M-4Px7UKxpKuWb9x96VFSnd8Msaog"
        }
      ],
      "services": {
        "appinvite_service": {
          "other_platform_oauth_client": []
        }
      }
    }
  ],
  "configuration_version": "1"
}